LICENSE
MANIFEST.in
README.md
setup.py
doc/Makefile
doc/api.rst
doc/conf.py
doc/index.rst
doc/make.bat
doc/tutorial.rst
pdblp/__init__.py
pdblp/_version.py
pdblp/parser.py
pdblp/pdblp.py
pdblp/utils.py
pdblp.egg-info/PKG-INFO
pdblp.egg-info/SOURCES.txt
pdblp.egg-info/dependency_links.txt
pdblp.egg-info/not-zip-safe
pdblp.egg-info/requires.txt
pdblp.egg-info/top_level.txt
pdblp/tests/__init__.py
pdblp/tests/conftest.py
pdblp/tests/test_parser.py
pdblp/tests/test_pdblp.py
pdblp/tests/data/bulkref_20150530.csv
pdblp/tests/data/bulkref_20150530_20160530.csv
pdblp/tests/data/bulkref_two_fields_20150530.csv