Metadata-Version: 1.0
Name: pdblp
Version: 0.1.7
Summary: Bloomberg Open API with pandas
Home-page: https://github.com/MatthewGilbert/pdblp
Author: Matthew Gilbert
Author-email: matthew.gilbert12@gmail.com
License: MIT
Platform: any
